xades/__init__.py
xades/constants.py
xades/ns.py
xades/object_identifier.py
xades/policy.py
xades/template.py
xades/utils.py
xades/xades_context.py
xades/data/XAdES.xsd
xades/data/xmldsig-core-schema.xsd
xades-0.2.4.dist-info/LICENSE
xades-0.2.4.dist-info/METADATA
xades-0.2.4.dist-info/WHEEL
xades-0.2.4.dist-info/top_level.txt
xades-0.2.4.dist-info/RECORD
