Metadata-Version: 2.1
Name: xades
Version: 0.2.4
Summary: XaDES XML signature
Home-page: http://github.com/etobella/python-xades
Author: Enric Tobella Alomar
Author-email: etobella@creublanca.es
License: AGPL-3
Platform: UNKNOWN
Classifier: Development Status :: 4 - Beta
Classifier: License :: OSI Approved :: GNU Affero General Public License v3
Classifier: Programming Language :: Python :: 2
Classifier: Programming Language :: Python :: 2.7
Classifier: Programming Language :: Python :: 3
Classifier: Programming Language :: Python :: 3.5
Classifier: Programming Language :: Python :: 3.6
Classifier: Programming Language :: Python :: 3.7
Requires-Dist: pytz
Requires-Dist: xmlsig
Provides-Extra: test
Requires-Dist: xmlsig[test] ; extra == 'test'
